Metadata-Version: 2.1
Name: base58grs
Version: 2.1.1
Summary: Base58 and Base58Check implementation for Groestlcoin.
Home-page: https://github.com/Groestlcoin/base58grs
Author: groestlcoin developers
Author-email: groestlcoin@gmail.com
License: MIT
Platform: UNKNOWN
Classifier: Development Status :: 5 - Production/Stable
Classifier: Intended Audience :: Developers
Classifier: License :: OSI Approved :: MIT License
Classifier: Programming Language :: Python
Classifier: Programming Language :: Python :: 3
Requires-Python: >=3.5
Provides-Extra: tests
